xpycode_master/__init__.py
xpycode_master/__main__.py
xpycode_master/config.py
xpycode_master/launcher.py
xpycode_master/logging_config.py
xpycode_master/mkdocs.yml
xpycode_master/watchdog_xpc.py
xpycode_master/addin_launcher/__init__.py
xpycode_master/addin_launcher/__main__.py
xpycode_master/addin_launcher/certificate_manager.py
xpycode_master/addin_launcher/cli.py
xpycode_master/addin_launcher/config.py
xpycode_master/addin_launcher/exceptions.py
xpycode_master/addin_launcher/py.typed
xpycode_master/addin_launcher/server_manager.py
xpycode_master/addin_launcher/bin/.gitkeep
xpycode_master/addin_launcher/bin/addin-server-linux
xpycode_master/addin_launcher/bin/addin-server-macos
xpycode_master/addin_launcher/bin/addin-server-win.exe
xpycode_master/addin_launcher/bin/manifest/.gitkeep
xpycode_master/addin_launcher/bin/manifest/manifest.xml
xpycode_master/addin_launcher/bin/resources/config.json
xpycode_master/addin_launcher/bin/resources/favicon.ico
xpycode_master/addin_launcher/bin/resources/functions.html
xpycode_master/addin_launcher/bin/resources/functions.js
xpycode_master/addin_launcher/bin/resources/functions.json
xpycode_master/addin_launcher/bin/resources/message-box-dialog.html
xpycode_master/addin_launcher/bin/resources/styles.css
xpycode_master/addin_launcher/bin/resources/taskpane.html
xpycode_master/addin_launcher/bin/resources/taskpane.js
xpycode_master/addin_launcher/bin/resources/assets/console-16.png
xpycode_master/addin_launcher/bin/resources/assets/console-32.png
xpycode_master/addin_launcher/bin/resources/assets/console-80.png
xpycode_master/addin_launcher/bin/resources/assets/error-icon-16.png
xpycode_master/addin_launcher/bin/resources/assets/error-icon-32.png
xpycode_master/addin_launcher/bin/resources/assets/error-icon-80.png
xpycode_master/addin_launcher/bin/resources/assets/icon-16.png
xpycode_master/addin_launcher/bin/resources/assets/icon-32.png
xpycode_master/addin_launcher/bin/resources/assets/icon-64.png
xpycode_master-0.1.3.dist-info/licenses/LICENSE
xpycode_master-0.1.3.dist-info/METADATA
xpycode_master-0.1.3.dist-info/WHEEL
xpycode_master-0.1.3.dist-info/entry_points.txt
xpycode_master-0.1.3.dist-info/top_level.txt
xpycode_master-0.1.3.dist-info/RECORD
