Metadata-Version: 2.4
Name: xpycode_master
Version: 0.1.3
Summary: XPyCode Master - Python scripting for Excel with VBA-like interface
Author: XPyCode Team
License-Expression: MIT
Project-URL: Homepage, https://xpycode.com
Project-URL: Repository, https://xpycode.com/repo
Project-URL: Issues, https://xpycode.com/issues
Project-URL: Documentation, https://docs.xpycode.com
Keywords: excel,python,vba,automation,office
Classifier: Development Status :: 3 - Alpha
Classifier: Intended Audience :: Developers
Classifier: Programming Language :: Python :: 3
Classifier: Programming Language :: Python :: 3.10
Classifier: Programming Language :: Python :: 3.11
Classifier: Programming Language :: Python :: 3.12
Classifier: Programming Language :: Cython
Classifier: Operating System :: OS Independent
Classifier: Topic :: Office/Business
Classifier: Topic :: Software Development :: Libraries :: Python Modules
Requires-Python: >=3.10
License-File: LICENSE
Requires-Dist: fastapi>=0.115.0
Requires-Dist: uvicorn>=0.30.0
Requires-Dist: websockets>=12.0
Requires-Dist: aiohttp>=3.9.0
Requires-Dist: packaging>=21.0
Requires-Dist: python-lsp-server>=1.9.0
Requires-Dist: jedi>=0.18.0
Requires-Dist: pyflakes>=3.0.0
Requires-Dist: cryptography>=3.0
Requires-Dist: pip-system-certs
Requires-Dist: requests-ntlm
Requires-Dist: PySide6>=6.6.0
Requires-Dist: qasync>=0.27.0
Requires-Dist: keyring>=24.0.0
Requires-Dist: pandas>=2.0.0
Requires-Dist: mkdocs>=1.5.3
Requires-Dist: mkdocs-material>=9.5.0
Requires-Dist: mkdocs-glightbox>=0.3.7
Requires-Dist: mkdocs-print-site-plugin>=2.3.0
Requires-Dist: pymdown-extensions>=10.7
Dynamic: license-file
